frequensee/__init__.py
frequensee/audio_viz.py
frequensee/cli.py
frequensee/config.py
frequensee/writers.py
frequensee-0.0.4.dist-info/METADATA
frequensee-0.0.4.dist-info/WHEEL
frequensee-0.0.4.dist-info/entry_points.txt
frequensee-0.0.4.dist-info/licenses/LICENSE
frequensee-0.0.4.dist-info/RECORD
