Metadata-Version: 2.4
Name: frequensee
Version: 0.0.4
Summary: A CLI tool that produces frequency animations for audio files with FFMPEG.
Project-URL: Homepage, https://github.com/AntonisTorb/Frequensee
Project-URL: Documentation, https://github.com/AntonisTorb/Frequensee
Project-URL: Repository, https://github.com/AntonisTorb/Frequensee.git
Project-URL: Issues, https://github.com/AntonisTorb/Frequensee/issues
Author-email: Antonios Stefanos Tormpantonis <antonistorb@yahoo.com>
Maintainer-email: Antonios Stefanos Tormpantonis <antonistorb@yahoo.com>
License-File: LICENSE
Keywords: animation,audio,cli,ffmpeg,frequency,visualizer
Classifier: Development Status :: 4 - Beta
Classifier: License :: OSI Approved :: MIT License
Classifier: Programming Language :: Python
Classifier: Topic :: Multimedia :: Sound/Audio :: Analysis
Classifier: Topic :: Multimedia :: Video
Classifier: Topic :: Scientific/Engineering :: Visualization
Requires-Python: >=3.9
Requires-Dist: matplotlib>=3.9.3
Requires-Dist: soundfile>=0.12.1
